strands_hubspot/__init__.py
strands_hubspot/hubspot.py
strands_hubspot/templates/__init__.py
strands_hubspot/templates/hubspot_examples.py
strands_hubspot-0.1.1.dist-info/licenses/LICENSE
strands_hubspot-0.1.1.dist-info/METADATA
strands_hubspot-0.1.1.dist-info/WHEEL
strands_hubspot-0.1.1.dist-info/top_level.txt
strands_hubspot-0.1.1.dist-info/RECORD
