Metadata-Version: 2.4
Name: strands-hubspot
Version: 0.1.1
Summary: HubSpot CRM tool for Strands Agents SDK
Home-page: https://github.com/eraykeskinmac/strands-hubspot
Author: Eray Keskin
Author-email: Eray Keskin <eraykeskinmac@gmail.com>
License: MIT
Project-URL: Homepage, https://github.com/eraykeskinmac/strands-hubspot
Project-URL: Documentation, https://github.com/eraykeskinmac/strands-hubspot
Project-URL: Repository, https://github.com/eraykeskinmac/strands-hubspot
Project-URL: Bug Reports, https://github.com/eraykeskinmac/strands-hubspot/issues
Keywords: strands,ai,agents,hubspot,crm,sales,marketing
Classifier: Development Status :: 4 - Beta
Classifier: Intended Audience :: Developers
Classifier: License :: OSI Approved :: MIT License
Classifier: Programming Language :: Python :: 3
Classifier: Programming Language :: Python :: 3.9
Classifier: Programming Language :: Python :: 3.10
Classifier: Programming Language :: Python :: 3.11
Classifier: Programming Language :: Python :: 3.12
Classifier: Topic :: Software Development :: Libraries :: Python Modules
Classifier: Topic :: Scientific/Engineering :: Artificial Intelligence
Requires-Python: >=3.9
License-File: LICENSE
Requires-Dist: strands-agents>=1.11.0
Requires-Dist: requests>=2.31.0
Requires-Dist: rich>=13.0.0
Provides-Extra: dev
Requires-Dist: pytest>=7.0.0; extra == "dev"
Requires-Dist: black>=23.0.0; extra == "dev"
Requires-Dist: flake8>=6.0.0; extra == "dev"
Dynamic: author
Dynamic: home-page
Dynamic: license-file
Dynamic: requires-python
